ClustSim/__init__.py
ClustSim/plot_clusters.py
ClustSim/simulate_clusters.py
ClustSim-1.0.0.dist-info/LICENSE
ClustSim-1.0.0.dist-info/METADATA
ClustSim-1.0.0.dist-info/WHEEL
ClustSim-1.0.0.dist-info/top_level.txt
ClustSim-1.0.0.dist-info/RECORD
