Metadata-Version: 2.1
Name: ClustSim
Version: 1.0.0
Summary: Cluster simulations
Home-page: https://github.com/Kaufman-Lab-Columbia/ClustSim
Author: Joseph L. Hammer, Alexander J. Devanny
Author-email: jhammer3018@gmail.com
License: MIT
Keywords: cluster clusters clustering simulation simulate
Classifier: License :: OSI Approved :: MIT License
Classifier: Programming Language :: Python :: 3
Classifier: Topic :: Scientific/Engineering
License-File: LICENSE
Requires-Dist: numpy<2,>=1.20.0
Requires-Dist: matplotlib>=3.5
Requires-Dist: scikit-learn>=1.3
